saf/__init__.py
saf/annotators/__init__.py
saf/annotators/annotator.py
saf/constants/__init__.py
saf/constants/annotation.py
saf/data_model/__init__.py
saf/data_model/annotable.py
saf/data_model/document.py
saf/data_model/sentence.py
saf/data_model/sequence.py
saf/data_model/token.py
saf/data_model/vocabulary.py
saf/formatters/__init__.py
saf/formatters/conll.py
saf/formatters/plain.py
saf/importers/__init__.py
saf/importers/conll.py
saf/importers/importer.py
saf/importers/list.py
saf/importers/morphodb.py
saf/importers/plain.py
saf/importers/webanno.py
saf/importers/tokenizers/__init__.py
saf/importers/tokenizers/conll.py
saf/test/__init__.py
saf/test/test_formatters.py
saf/test/test_importers.py
saf_nlp-0.6.1.dist-info/licenses/LICENSE
saf_nlp-0.6.1.dist-info/METADATA
saf_nlp-0.6.1.dist-info/WHEEL
saf_nlp-0.6.1.dist-info/top_level.txt
saf_nlp-0.6.1.dist-info/RECORD
