Metadata-Version: 2.4
Name: saf-nlp
Version: 0.6.1
Summary: Simple Annotation Framework
Home-page: 
Author: ['Danilo S. Carvalho', 'Vu Duc Tran']
Author-email: "Danilo S. Carvalho" <danilo.carvalho@manchester.ac.uk>, Vu Duc Tran <vu.tran@jaist.ac.jp>
License-Expression: GPL-3.0-or-later
Project-URL: Homepage, https://github.com/dscarvalho/saf
Project-URL: Issues, https://github.com/dscarvalho/saf/issues
Keywords: annotation,nlp
Classifier: Programming Language :: Python :: 3
Classifier: Operating System :: OS Independent
Requires-Python: >=3.7
License-File: LICENSE
Requires-Dist: nltk
Requires-Dist: regex
Dynamic: author
Dynamic: license-file
